rabbitmq_admin/__init__.py
rabbitmq_admin/api.py
rabbitmq_admin/base.py
rabbitmq_api_admin-0.4.0.dist-info/LICENSE
rabbitmq_api_admin-0.4.0.dist-info/METADATA
rabbitmq_api_admin-0.4.0.dist-info/WHEEL
rabbitmq_api_admin-0.4.0.dist-info/RECORD
