Metadata-Version: 2.1
Name: rabbitmq-api-admin
Version: 0.4.0
Summary: A python interface for the RabbitMQ Admin HTTP API
Home-page: https://github.com/Uma-Tech/rabbitmq-api-admin
License: Apache-2.0
Author: UMA.TECH
Author-email: developers@uma.tech
Requires-Python: >=3.8,<4.0
Classifier: License :: OSI Approved :: Apache Software License
Classifier: Programming Language :: Python :: 3
Classifier: Programming Language :: Python :: 3.8
Classifier: Programming Language :: Python :: 3.9
Classifier: Programming Language :: Python :: 3.10
Classifier: Programming Language :: Python :: 3.11
Requires-Dist: requests (>=2.28.1,<3.0.0)
Project-URL: Repository, https://github.com/Uma-Tech/rabbitmq-api-admin
